[
  {
    "nombre": "Ver Ahora",
    "link": "https://ejemplo.com/evento1",
    "dispositivos": ["ios", "android", "pc"],
    "inicio": "2025-09-28T16:00:00",
    "fin": "2025-09-28T19:00:00"
  },
  {
    "nombre": "Ver Ahora",
    "link": "https://ejemplo.com/evento2",
    "dispositivos": ["android", "pc"],
    "inicio": "2025-09-28T16:00:00",
    "fin": "2025-09-28T19:00:00"
  },
  {
    "nombre": "Ver Ahora",
    "link": "https://ejemplo.com/evento3",
    "dispositivos": ["ios"],
    "inicio": "2025-09-28T16:00:00",
    "fin": "2025-09-28T19:00:00"
  }
]
